po_projects_client
