Metadata-Version: 1.1
Name: PO-Projects-client
Version: 0.1
Summary: 
